pyLDAvis/__init__.py
pyLDAvis/_display.py
pyLDAvis/_prepare.py
pyLDAvis/_server.py
pyLDAvis/gensim.py
pyLDAvis/gensim_models.py
pyLDAvis/graphlab.py
pyLDAvis/lda_model.py
pyLDAvis/urls.py
pyLDAvis/utils.py
pyLDAvis/js/d3.v5.min.js
pyLDAvis/js/ldavis.css
pyLDAvis/js/ldavis.js
pyLDAvis/js/ldavis.v1.0.0.css
pyLDAvis/js/ldavis.v1.0.0.js
pyLDAvis/js/ldavis.v3.0.0.js
pyLDAvis/lib/python3.11/site-packages/_distutils_hack/__init__.py
pyLDAvis/lib/python3.11/site-packages/_distutils_hack/override.py
pyLDAvis/lib/python3.11/site-packages/pip/__init__.py
pyLDAvis/lib/python3.11/site-packages/pip/__main__.py
pyLDAvis/lib/python3.11/site-packages/pip/__pip-runner__.py
pyLDAvis/lib/python3.11/site-packages/pip/_internal/__init__.py
pyLDAvis/lib/python3.11/site-packages/pip/_internal/build_env.py
pyLDAvis/lib/python3.11/site-packages/pip/_internal/cache.py
pyLDAvis/lib/python3.11/site-packages/pip/_internal/configuration.py
pyLDAvis/lib/python3.11/site-packages/pip/_internal/exceptions.py
pyLDAvis/lib/python3.11/site-packages/pip/_internal/main.py
pyLDAvis/lib/python3.11/site-packages/pip/_internal/pyproject.py
pyLDAvis/lib/python3.11/site-packages/pip/_internal/self_outdated_check.py
pyLDAvis/lib/python3.11/site-packages/pip/_internal/wheel_builder.py
pyLDAvis/lib/python3.11/site-packages/pip/_internal/cli/__init__.py
pyLDAvis/lib/python3.11/site-packages/pip/_internal/cli/autocompletion.py
pyLDAvis/lib/python3.11/site-packages/pip/_internal/cli/base_command.py
pyLDAvis/lib/python3.11/site-packages/pip/_internal/cli/cmdoptions.py
pyLDAvis/lib/python3.11/site-packages/pip/_internal/cli/command_context.py
pyLDAvis/lib/python3.11/site-packages/pip/_internal/cli/main.py
pyLDAvis/lib/python3.11/site-packages/pip/_internal/cli/main_parser.py
pyLDAvis/lib/python3.11/site-packages/pip/_internal/cli/parser.py
pyLDAvis/lib/python3.11/site-packages/pip/_internal/cli/progress_bars.py
pyLDAvis/lib/python3.11/site-packages/pip/_internal/cli/req_command.py
pyLDAvis-3.4.1.dist-info/AUTHORS.rst
pyLDAvis-3.4.1.dist-info/LICENSE
pyLDAvis-3.4.1.dist-info/METADATA
pyLDAvis-3.4.1.dist-info/WHEEL
pyLDAvis-3.4.1.dist-info/top_level.txt
pyLDAvis-3.4.1.dist-info/RECORD
