Metadata-Version: 2.1
Name: pyLDAvis
Version: 3.4.1
Summary: Interactive topic model visualization. Port of the R package.
Home-page: https://github.com/bmabey/pyLDAvis
Download-URL: https://github.com/bmabey/pyLDAvis/tarball/3.4.1
Author: Ben Mabey
Author-email: ben@benmabey.com
License: BSD-3-Clause
Keywords: data science,visualization
Classifier: Development Status :: 5 - Production/Stable
Classifier: Intended Audience :: Developers
Classifier: Intended Audience :: Science/Research
Classifier: License :: OSI Approved :: BSD License
Classifier: Natural Language :: English
Classifier: Programming Language :: Python :: 3
Classifier: Programming Language :: Python :: 3.9
Classifier: Programming Language :: Python :: 3.10
Classifier: Programming Language :: Python :: 3.11
Requires-Python: >=3.9
License-File: LICENSE
License-File: AUTHORS.rst
